mcp_server_unitycatalog/__init__.py
mcp_server_unitycatalog/__main__.py
mcp_server_unitycatalog/cli.py
mcp_server_unitycatalog/config.py
mcp_server_unitycatalog/logger.py
mcp_server_unitycatalog/server.py
mcp_server_unitycatalog/tools.py
mcp_server_unitycatalog/utils.py
mseep_mcp_server_unitycatalog-0.1.4.dist-info/licenses/LICENSE
mseep_mcp_server_unitycatalog-0.1.4.dist-info/METADATA
mseep_mcp_server_unitycatalog-0.1.4.dist-info/WHEEL
mseep_mcp_server_unitycatalog-0.1.4.dist-info/entry_points.txt
mseep_mcp_server_unitycatalog-0.1.4.dist-info/top_level.txt
mseep_mcp_server_unitycatalog-0.1.4.dist-info/RECORD
